{"nodes": [{"id": "c_users_evert_downloads_marketscoupons_repo_scripts_render_tradeday_mockup_js", "label": "render-tradeday-mockup.js", "file_type": "code", "source_file": "c:\\Users\\evert\\Downloads\\marketscoupons-repo\\scripts\\render-tradeday-mockup.js", "source_location": "L1"}, {"id": "scripts_render_tradeday_mockup_chromium", "label": "{ chromium }", "file_type": "code", "source_file": "c:\\Users\\evert\\Downloads\\marketscoupons-repo\\scripts\\render-tradeday-mockup.js", "source_location": "L1"}, {"id": "scripts_render_tradeday_mockup_path", "label": "path", "file_type": "code", "source_file": "c:\\Users\\evert\\Downloads\\marketscoupons-repo\\scripts\\render-tradeday-mockup.js", "source_location": "L2"}, {"id": "scripts_render_tradeday_mockup_targets", "label": "targets", "file_type": "code", "source_file": "c:\\Users\\evert\\Downloads\\marketscoupons-repo\\scripts\\render-tradeday-mockup.js", "source_location": "L4"}, {"id": "scripts_render_tradeday_mockup_src", "label": "src", "file_type": "code", "source_file": "c:\\Users\\evert\\Downloads\\marketscoupons-repo\\scripts\\render-tradeday-mockup.js", "source_location": "L15"}, {"id": "scripts_render_tradeday_mockup_abs", "label": "abs", "file_type": "code", "source_file": "c:\\Users\\evert\\Downloads\\marketscoupons-repo\\scripts\\render-tradeday-mockup.js", "source_location": "L17"}], "edges": [{"source": "c_users_evert_downloads_marketscoupons_repo_scripts_render_tradeday_mockup_js", "target": "playwright", "relation": "imports_from", "context": "import", "confidence": "EXTRACTED", "source_file": "c:\\Users\\evert\\Downloads\\marketscoupons-repo\\scripts\\render-tradeday-mockup.js", "source_location": "L1", "weight": 1.0}, {"source": "c_users_evert_downloads_marketscoupons_repo_scripts_render_tradeday_mockup_js", "target": "scripts_render_tradeday_mockup_chromium", "relation": "contains", "confidence": "EXTRACTED", "source_file": "c:\\Users\\evert\\Downloads\\marketscoupons-repo\\scripts\\render-tradeday-mockup.js", "source_location": "L1", "weight": 1.0}, {"source": "c_users_evert_downloads_marketscoupons_repo_scripts_render_tradeday_mockup_js", "target": "path", "relation": "imports_from", "context": "import", "confidence": "EXTRACTED", "source_file": "c:\\Users\\evert\\Downloads\\marketscoupons-repo\\scripts\\render-tradeday-mockup.js", "source_location": "L2", "weight": 1.0}, {"source": "c_users_evert_downloads_marketscoupons_repo_scripts_render_tradeday_mockup_js", "target": "scripts_render_tradeday_mockup_path", "relation": "contains", "confidence": "EXTRACTED", "source_file": "c:\\Users\\evert\\Downloads\\marketscoupons-repo\\scripts\\render-tradeday-mockup.js", "source_location": "L2", "weight": 1.0}, {"source": "c_users_evert_downloads_marketscoupons_repo_scripts_render_tradeday_mockup_js", "target": "scripts_render_tradeday_mockup_targets", "relation": "contains", "confidence": "EXTRACTED", "source_file": "c:\\Users\\evert\\Downloads\\marketscoupons-repo\\scripts\\render-tradeday-mockup.js", "source_location": "L4", "weight": 1.0}, {"source": "c_users_evert_downloads_marketscoupons_repo_scripts_render_tradeday_mockup_js", "target": "scripts_render_tradeday_mockup_src", "relation": "contains", "confidence": "EXTRACTED", "source_file": "c:\\Users\\evert\\Downloads\\marketscoupons-repo\\scripts\\render-tradeday-mockup.js", "source_location": "L15", "weight": 1.0}, {"source": "c_users_evert_downloads_marketscoupons_repo_scripts_render_tradeday_mockup_js", "target": "scripts_render_tradeday_mockup_abs", "relation": "contains", "confidence": "EXTRACTED", "source_file": "c:\\Users\\evert\\Downloads\\marketscoupons-repo\\scripts\\render-tradeday-mockup.js", "source_location": "L17", "weight": 1.0}], "raw_calls": []}